enipy/__init__.py
enipy/ellipsoidalVincenty.py
enipy/lxTools.py
enipy/lxcTools_setup.py
enipy/miscTools.py
enipy/visTools.py
enipy-0.50.dist-info/METADATA
enipy-0.50.dist-info/RECORD
enipy-0.50.dist-info/WHEEL
enipy-0.50.dist-info/top_level.txt
