Metadata-Version: 2.1
Name: enipy
Version: 0.50
Summary: Tool for analyzing Lightning Data
Home-page: UNKNOWN
Author: Micheal Stock
Author-email: mstock@earthnetworks.com
License: UNKNOWN
Platform: UNKNOWN
